{
    "새라시":{
        "날씨": {"1월":5,"2월":7,"3월":8,"4월":9,"5월":20,"6월":22,"7월":23,"8월":20,"9월":19,"10월":10,"11월":5,"12월":-3},
        "인구": 21322,
        "민주당":20000,
        "한국당":1322,
        "인구구성비":[{"name":"1990년","14세이하": 25.6,"14~64세": 69.3, "65세이상": 5.1},
            {"name":"2000년","14세이하": 21.1,"14~64세": 71.7, "65세이상": 7.2},
            {"name":"2010년","14세이하": 16.1,"14~64세": 73.1, "65세이상": 10.8},
            {"name":"2020년","14세이하": 12.7,"14~64세": 71.7, "65세이상": 15.6}],
        "주거형태":[{"name": "아파트", "value": 700}, {"name": "다세대", "value": 200},
                    {"name": "연립", "value": 500}, {"name":" 기타", "value": 200}]
    },   
    "나래시":{
        "날씨": 
        {"1월":31,"2월":32,"3월":33,"4월":34,"5월":34,"6월":33,"7월":30,"8월":29,"9월":27,"10월":26,"11월":25,"12월":21},
        "인구": 32332,
        "민주당":30000,
        "한국당":2332,
        "인구구성비":[{"name":"1990년","14세이하": 14.0,"14~64세": 69.8, "65세이상": 16.2},
                    {"name":"2000년","14세이하": 11.4,"14~64세": 66.9, "65세이상": 21.7},
                    {"name":"2010년","14세이하": 9.8,"14~64세": 61.1, "65세이상": 29.1},
                    {"name":"2020년","14세이하": 8.8,"14~64세": 59.4, "65세이상": 31.8}],
        "주거형태":[{"name": "아파트", "value": 200}, {"name": "다세대", "value": 700},
                        {"name": "연립", "value": 200}, {"name":" 기타", "value": 200}]            
    },
    "아라시":{
        "날씨": 
        {"1월":31,"2월":32,"3월":33,"4월":34,"5월":34,"6월":33,"7월":30,"8월":29,"9월":27,"10월":26,"11월":25,"12월":21},
        "인구": 32332,
        "민주당":30000,
        "한국당":2332,
        "인구구성비":[{"name":"1990년","14세이하": 13.2,"14~64세": 74.6, "65세이상": 12.2},
                    {"name":"2000년","14세이하": 12.1,"14~64세": 69.1, "65세이상": 18.8},
                    {"name":"2010년","14세이하": 9.2,"14~64세": 67.7, "65세이상": 23.1},
                    {"name":"2020년","14세이하": 6.7,"14~64세":62.8, "65세이상": 30.5}],
        "주거형태":[{"name": "아파트", "value": 300}, {"name": "다세대", "value": 600},
                        {"name": "연립", "value": 500}, {"name":" 기타", "value": 200}]
    },
    "마루시":{
        "날씨": 
        {"1월":31,"2월":32,"3월":33,"4월":34,"5월":34,"6월":33,"7월":30,"8월":29,"9월":27,"10월":26,"11월":25,"12월":21},
        "인구": 32332,
        "민주당":30000,
        "한국당":2332,
        "인구구성비":[{"name":"1990년","14세이하": 23.4,"14~64세": 70.7, "65세이상": 5.9},
                    {"name":"2000년","14세이하": 12.8,"14~64세": 73.4, "65세이상": 12.8},
                    {"name":"2010년","14세이하": 11.3,"14~64세": 60.0, "65세이상": 28.7},
                    {"name":"2020년","14세이하": 10.1,"14~64세": 54.3, "65세이상": 35.6}],
        "주거형태":[{"name": "아파트", "value": 200}, {"name": "다세대", "value": 200},
                {"name": "연립", "value": 500}, {"name":" 기타", "value": 200}]
    }
}